celescope/__init__.py
celescope/celescope.py
celescope/bulk_vdj/__init__.py
celescope/bulk_vdj/consensus.py
celescope/bulk_vdj/count_vdj.py
celescope/bulk_vdj/mapping_vdj.py
celescope/bulk_vdj/multi_bulk_vdj.py
celescope/bulk_vdj/tmp_cutadapt.py
celescope/convert10X/__init__.py
celescope/convert10X/cellranger.py
celescope/convert10X/multi_convert10X.py
celescope/data/chemistry/737K-august-2016.txt
celescope/data/chemistry/bulk_vdj/bclist
celescope/data/chemistry/bulk_vdj/linker
celescope/data/chemistry/flv/bclist
celescope/data/chemistry/flv/linker
celescope/data/chemistry/flv-V2/bclist
celescope/data/chemistry/flv-V2/linker
celescope/data/chemistry/flv_rna/bclist
celescope/data/chemistry/flv_rna/linker_4types
celescope/data/chemistry/scopeV2.0.0/bclist
celescope/data/chemistry/scopeV2.0.0/linker
celescope/data/chemistry/scopeV2.0.1/bclist
celescope/data/chemistry/scopeV2.0.1/linker_withC
celescope/data/chemistry/scopeV2.1.0/bclist
celescope/data/chemistry/scopeV2.1.0/linker
celescope/data/chemistry/scopeV2.1.1/bclist
celescope/data/chemistry/scopeV2.1.1/linker_withC
celescope/data/chemistry/scopeV2.2.1/bclist
celescope/data/chemistry/scopeV2.2.1/linker_4types
celescope/data/chemistry/scopeV3.0.1/bclist
celescope/data/chemistry/scopeV3.0.1/linker_4types
celescope/flv_CR/__init__.py
celescope/flv_CR/assemble.py
celescope/flv_CR/check.py
celescope/flv_CR/convert.py
celescope/flv_CR/mapping.py
celescope/flv_CR/match.py
celescope/flv_CR/multi_flv_CR.py
celescope/flv_CR/refine_assemble.py
celescope/flv_CR/summarize.py
celescope/flv_trust4/__init__.py
celescope/flv_trust4/annotation.py
celescope/flv_trust4/assemble.py
celescope/flv_trust4/mapping.py
celescope/flv_trust4/multi_flv_trust4.py
celescope/flv_trust4/summarize.py
celescope/templates/css/bootstrap.min.css
celescope/templates/css/buttons.dataTables.min.css
celescope/templates/css/dataTables.jqueryui.min.css
celescope/templates/css/jquery-ui-git.css
celescope/templates/css/jquery-ui.css
singlecell_vdj-2.1.0.dist-info/licenses/LICENSE
singlecell_vdj-2.1.0.dist-info/METADATA
singlecell_vdj-2.1.0.dist-info/WHEEL
singlecell_vdj-2.1.0.dist-info/entry_points.txt
singlecell_vdj-2.1.0.dist-info/top_level.txt
singlecell_vdj-2.1.0.dist-info/RECORD
